tergiversate/__init__.py
tergiversate/locales/ar/LC_MESSAGES/tergiversate.mo
tergiversate/locales/bn/LC_MESSAGES/tergiversate.mo
tergiversate/locales/de/LC_MESSAGES/tergiversate.mo
tergiversate/locales/en/LC_MESSAGES/tergiversate.mo
tergiversate/locales/es/LC_MESSAGES/tergiversate.mo
tergiversate/locales/hi/LC_MESSAGES/tergiversate.mo
tergiversate/locales/ja/LC_MESSAGES/tergiversate.mo
tergiversate/locales/ko/LC_MESSAGES/tergiversate.mo
tergiversate/locales/pt/LC_MESSAGES/tergiversate.mo
tergiversate/locales/uk/LC_MESSAGES/tergiversate.mo
tergiversate/locales/zh/LC_MESSAGES/tergiversate.mo
tergiversator-0.8.4.data/scripts/tergiversator
tergiversator-0.8.4.dist-info/licenses/COPYING
tergiversator-0.8.4.dist-info/METADATA
tergiversator-0.8.4.dist-info/WHEEL
tergiversator-0.8.4.dist-info/top_level.txt
tergiversator-0.8.4.dist-info/RECORD
